Workbook
Name aporte: Investimentos!$D$17
Name patrimonio: Investimentos!$D$20
Name qtd_anos: Investimentos!$D$18
Name rendimento_carteira: Investimentos!$D$13
Name sugestao_investimento: Investimentos!$D$14
Name taxa_mensal: Investimentos!$D$19

Sheet Investimentos
B11: CONFIGURAÇÕES
B12: Salário | D12: 4000
B13: Rendimento da Carteira | D13: 0.01079
B14: Sugestão de Investimento(30%) | D14: =D12*30% -> 1200
B16: INVESTIMENTO MENSAL
B17: Quanto Investir por Mês ? | D17: 1200
B18: Por Quantos Anos ? | D18: 10
B19: Taxa de rendimento Mensal? | D19: 0.01079
B20: Patrimônio Acumulado? | D20: =FV(taxa_mensal,qtd_anos*12,aporte*-1) -> 291941.06
B21: Dividendos Mensais? | D21: =patrimonio*rendimento_carteira -> 3150.044
B23: Cenários | D23: Dividendo
A24: 2 | B24: Quanto teria 2 Anos? | C24: =FV($D$19,$A24*12,$D$17*-1) -> 32673.153 | D24: =C24*rendimento_carteira -> 352.54332
A25: 5 | B25: Quanto teria 5 Anos? | C25: =FV($D$19,$A25*12,$D$17*-1) -> 100532.3 | D25: =C25*rendimento_carteira -> 1084.7435
A26: 10 | B26: Quanto teria 10 Anos? | C26: =FV($D$19,$A26*12,$D$17*-1) -> 291941.06 | D26: =C26*rendimento_carteira -> 3150.044
A27: 20 | B27: Quanto teria 20 Anos? | C27: =FV($D$19,$A27*12,$D$17*-1) -> 1350238.1 | D27: =C27*rendimento_carteira -> 14569.069
A28: 30 | B28: Quanto teria 30 Anos? | C28: =FV($D$19,$A28*12,$D$17*-1) -> 5186603.6 | D28: =C28*rendimento_carteira -> 55963.453
B31: Perfil | C31: CONSERVADOR
B32: VALOR A SER INVESTIDO POR MÊS | C32: =aporte -> 1200
B34: TIPO FII | C34: PERCETUAL SUGERIDO | D34: VALORES
B35: PAPEL | C35: =VLOOKUP($C$31&"-"&B35,Apoio!$A:$D,4,FALSE) -> 0.3 | D35: =C35*$C$32 -> 360
B36: TIJOLO | C36: =VLOOKUP($C$31&"-"&B36,Apoio!$A:$D,4,FALSE) -> 0.5 | D36: =C36*$C$32 -> 600
B37: HÍBRIDOS | C37: =VLOOKUP($C$31&"-"&B37,Apoio!$A:$D,4,FALSE) -> 0.1 | D37: =C37*$C$32 -> 120
B38: FOFs | C38: =VLOOKUP($C$31&"-"&B38,Apoio!$A:$D,4,FALSE) -> 0.1 | D38: =C38*$C$32 -> 120
B39: DESENVOLVIMENTO | C39: =VLOOKUP($C$31&"-"&B39,Apoio!$A:$D,4,FALSE) -> 0 | D39: =C39*$C$32 -> 0
B40: HOTELARIAS | C40: =VLOOKUP($C$31&"-"&B40,Apoio!$A:$D,4,FALSE) -> 0 | D40: =C40*$C$32 -> 0
D41: =SUM(D35:D40) -> 1200

Sheet Apoio
A2: CHAVE COMPOSTA | B2: PERFIL | C2: TIPO DE FII | D2: %
A3: =B3&"-"&C3 -> CONSERVADOR-PAPEL | B3: CONSERVADOR | C3: PAPEL | D3: 0.3
A4: =B4&"-"&C4 -> CONSERVADOR-TIJOLO | B4: CONSERVADOR | C4: TIJOLO | D4: 0.5
A5: =B5&"-"&C5 -> CONSERVADOR-HÍBRIDOS | B5: CONSERVADOR | C5: HÍBRIDOS | D5: 0.1 | H5: MODERADO-TIJOLO | I5: =VLOOKUP(H5,$A:$D,4,FALSE) -> 0.35
A6: =B6&"-"&C6 -> CONSERVADOR-FOFs | B6: CONSERVADOR | C6: FOFs | D6: 0.1
A7: =B7&"-"&C7 -> CONSERVADOR-DESENVOLVIMENTO | B7: CONSERVADOR | C7: DESENVOLVIMENTO | D7: 0
A8: =B8&"-"&C8 -> CONSERVADOR-HOTELARIAS | B8: CONSERVADOR | C8: HOTELARIAS | D8: 0
A9: =B9&"-"&C9 -> MODERADO-PAPEL | B9: MODERADO | C9: PAPEL | D9: 0.32
A10: =B10&"-"&C10 -> MODERADO-TIJOLO | B10: MODERADO | C10: TIJOLO | D10: 0.35
A11: =B11&"-"&C11 -> MODERADO-HÍBRIDOS | B11: MODERADO | C11: HÍBRIDOS | D11: 0.08
A12: =B12&"-"&C12 -> MODERADO-FOFs | B12: MODERADO | C12: FOFs | D12: 0.05
A13: =B13&"-"&C13 -> MODERADO-DESENVOLVIMENTO | B13: MODERADO | C13: DESENVOLVIMENTO | D13: 0.1
A14: =B14&"-"&C14 -> MODERADO-HOTELARIAS | B14: MODERADO | C14: HOTELARIAS | D14: 0.1
A15: =B15&"-"&C15 -> AGRESSIVO-PAPEL | B15: AGRESSIVO | C15: PAPEL | D15: 0.5
A16: =B16&"-"&C16 -> AGRESSIVO-TIJOLO | B16: AGRESSIVO | C16: TIJOLO | D16: 0.1
A17: =B17&"-"&C17 -> AGRESSIVO-HÍBRIDOS | B17: AGRESSIVO | C17: HÍBRIDOS | D17: 0.05
... A20: =B20&"-"&C20 -> AGRESSIVO-HOTELARIAS | B20: AGRESSIVO | C20: HOTELARIAS | D20: 0.1
